README.rst
setup.py
memecli/__init__.py
memecli/main.py
memecli.egg-info/PKG-INFO
memecli.egg-info/SOURCES.txt
memecli.egg-info/dependency_links.txt
memecli.egg-info/entry_points.txt
memecli.egg-info/not-zip-safe
memecli.egg-info/requires.txt
memecli.egg-info/top_level.txt