Metadata-Version: 1.1
Name: memecli
Version: 0.4
Summary: Command line wrapper over http://memegenerator.net API.
Home-page: https://github.com/surrealists/memecli
Author: Cabrera Cabrera
Author-email: surrealcristian@gmail.com
License: MIT
Platform: UNKNOWN
Classifier: Development Status :: 1 - Planning
Classifier: Environment :: Console
Classifier: Intended Audience :: Developers
Classifier: Intended Audience :: Other Audience
Classifier: Intended Audience :: System Administrators
Classifier: License :: OSI Approved :: MIT License
Classifier: Natural Language :: English
Classifier: Programming Language :: Python :: 2
Classifier: Programming Language :: Python :: 3
Classifier: Programming Language :: Python :: Implementation :: CPython
Classifier: Topic :: Internet
Classifier: Topic :: Utilities
